LogExportTable5.py
LogExportTable5-1.0.0.dist-info/METADATA
LogExportTable5-1.0.0.dist-info/WHEEL
LogExportTable5-1.0.0.dist-info/top_level.txt
LogExportTable5-1.0.0.dist-info/RECORD
