Metadata-Version: 2.1
Name: LogExportTable5
Version: 1.0.0
Summary: Log Export Table5
Author: SINTT
Author-email: bbhh66606@gmail.com
